scim_sim/__init__.py
scim_sim/cli.py
scim_sim-0.0.1.dist-info/METADATA
scim_sim-0.0.1.dist-info/WHEEL
scim_sim-0.0.1.dist-info/entry_points.txt
scim_sim-0.0.1.dist-info/licenses/LICENSE
scim_sim-0.0.1.dist-info/RECORD
