Metadata-Version: 2.4
Name: scim-sim
Version: 0.0.1
Summary: A SCIM directory simulator and management tool
Project-URL: Homepage, https://github.com/Avinash-Kamath/scim-sim
Author-email: Your Name <avinashmkamath@gmail.com>
License-File: LICENSE
Classifier: License :: OSI Approved :: MIT License
Classifier: Operating System :: OS Independent
Classifier: Programming Language :: Python :: 3
Requires-Python: >=3.6
Requires-Dist: faker>=18.0.0
Requires-Dist: fastapi>=0.68.0
Requires-Dist: requests>=2.28.0
Requires-Dist: uvicorn>=0.15.0
Provides-Extra: dev
Requires-Dist: black>=22.0.0; extra == 'dev'
Requires-Dist: flake8>=4.0.0; extra == 'dev'
Requires-Dist: pytest>=7.0.0; extra == 'dev'
